clerk_django/__init__.py
clerk_django/client.py
clerk_django/middlewares/__init__.py
clerk_django/middlewares/clerk.py
clerk_django/permissions/__init__.py
clerk_django/permissions/clerk.py
clerk_django/resources/__init__.py
clerk_django/resources/user.py
clerk_django-1.0.3.dist-info/LICENSE
clerk_django-1.0.3.dist-info/METADATA
clerk_django-1.0.3.dist-info/WHEEL
clerk_django-1.0.3.dist-info/top_level.txt
clerk_django-1.0.3.dist-info/RECORD
