Metadata-Version: 2.1
Name: clerk_django
Version: 1.0.3
Summary: A package for django rest framework to handle clerk authentication. It includes a auth middleware, permission and a wrapper around all the user related apis.
Author-email: Ravi Kumar Singh <ravikrsngh1999@gmail.com>
License: MIT License
Project-URL: Homepage, https://github.com/ravikrsngh/clerk_django
Project-URL: Issues, https://github.com/ravikrsngh/clerk_django/issues
Keywords: django,clerk,clerk django,clerk django package,integrate clerk and django
Requires-Python: >=3.8
License-File: LICENSE
Requires-Dist: PyJWT >=2.8.0
